[
  { "name": "CREME FRAICHE 34%", "price": "49,00" },
  { "name": "FRÜKOSTFLINGOR SPEC", "price": "21,50" },
  { "name": "GETOST ST MAURE Kampanj", "price": "25,00" },
  { "name": "GODIS LÖSVIKT", "price": "104,09" },
  { "name": "GUACAMOLE DIP MIX", "price": "21,90" },
  { "name": "GURKA STYCK", "price": "33,90" },
  { "name": "LAXFILE HELSIDA BỆN Kampanj", "price": "159,19" },
  { "name": "LÖK VIT G", "price": "22,95" },
  { "name": "ÖLIVER HALKIDIKI UR", "price": "26,50" },
  { "name": "PUMPA HALLOWEN", "price": "26,91" },
  { "name": "SKALKNIV CM", "price": "79,00" },
  { "name": "SMÖR OSALTAT", "price": "39,95" },
  { "name": "TOMAT PLOM-BABY", "price": "30,00" },
  { "name": "TORTILLA CHIPS CHEE", "price": "13,95" },
  { "name": "TORTILLA ORIGINAL L", "price": "20,95" },
  { "name": "VISPGRADDE 36%", "price": "40,95" },
  { "name": "YOGGI ORIG JDG/SMU", "price": "19,50" },
  { "name": "AGG 24-PACK 1428GR", "price": "79,90" },
  { "name": "ÖLKORV VITLÖK", "price": "42,50" },
  { "name": "SUMMERING RABATTER DETTA KÖP", "price": "63,05" },
  { "name": "ATT BETALA ( ARTIKLAR )", "price": "794,59" }
]
